{
  "type_id": "opinion",
  "type_name": "观点稿",
  "template_id": "default",
  "sections": [
    {
      "title": "深度观点/行业洞见标题",
      "bullets": [
        "包含行业核心关键词（如能源、金融、科技等）",
        "点明文章的核心论点或切入点（如投融资模式、政策影响）",
        "体现专业性与洞察力"
      ],
      "children": [],
      "description": "生成专业且具有深度的标题，通常采用“核心议题+分析角度”或“主标题|栏目名”的形式。",
      "word_count": "20-40字",
      "granularity": "高"
    },
    {
      "title": "导语",
      "bullets": [
        "宏观政策或行业大背景（如双碳、数字化转型）",
        "当前行业面临的主要矛盾或机遇",
        "文章的研究目的与核心议题概述"
      ],
      "children": [],
      "description": "阐述宏观背景，引出行业痛点或变革契机，并明确本文旨在探讨的核心问题。",
      "word_count": "150-200字",
      "granularity": "中"
    },
    {
      "title": "发展背景与现状",
      "bullets": [
        "行业演变的历史阶段回顾",
        "关键政策文件的发布及其推动作用",
        "市场规模、装机量或用户数等核心数据支撑",
        "当前基础设施、融资或技术层面的具体瓶颈"
      ],
      "children": [],
      "description": "详细回顾行业发展历程，引用数据佐证现状，并指出当前面临的具体瓶颈。",
      "word_count": "400-500字",
      "granularity": "详细"
    },
    {
      "title": "核心模式/机制解析",
      "bullets": [
        "对现有模式进行清晰的分类（如按产权、连接方式等）",
        "详细描述每种模式的运作逻辑与利益分配机制",
        "结合具体案例分析各模式的优劣势",
        "分析各模式下的风险点与收益特征"
      ],
      "children": [],
      "description": "对行业内的运作模式、商业模型或投融资方式进行分类与深度剖析。",
      "word_count": "600-800字",
      "granularity": "详细"
    },
    {
      "title": "解决方案与支持体系",
      "bullets": [
        "分析导致市场失灵或发展受阻的深层原因（如风险收益不匹配）",
        "政府/公共资本的介入方式（担保、贴息、引导基金）",
        "市场机构的创新举措（产品创新、服务下沉）",
        "多方协同（政府、企业、金融机构）的具体路径"
      ],
      "children": [],
      "description": "针对前文提出的瓶颈与风险，提出具体的解决方案，重点阐述外部支持（如金融、政策）的作用。",
      "word_count": "500-700字",
      "granularity": "详细"
    },
    {
      "title": "结语与展望",
      "bullets": [
        "重申行业发展的战略意义",
        "总结当前面临的挑战与机遇",
        "对不同参与主体（政府、国企、金融机构）提出具体建议",
        "展望未来的行业格局与社会价值"
      ],
      "children": [],
      "description": "总结全文核心观点，对行业未来的发展趋势提出建议与展望。",
      "word_count": "300-400字",
      "granularity": "中"
    },
    {
      "title": "作者与机构简介",
      "bullets": [
        "作者姓名与职称",
        "所属机构或基金会名称",
        "研究领域或专项介绍"
      ],
      "children": [],
      "description": "简要介绍文章作者的身份、职位及所属研究机构。",
      "word_count": "50-100字",
      "granularity": "低"
    }
  ],
  "meta": null
}